instruction_ner/__init__.py
instruction_ner/arg_parse.py
instruction_ner/collator.py
instruction_ner/dataset.py
instruction_ner/evaluate.py
instruction_ner/metrics.py
instruction_ner/model.py
instruction_ner/prepare_data.py
instruction_ner/train.py
instruction_ner/core/__init__.py
instruction_ner/core/datatypes.py
instruction_ner/core/reader.py
instruction_ner/formatters/Answer.py
instruction_ner/formatters/PredictionSpan.py
instruction_ner/formatters/__init__.py
instruction_ner/formatters/instances/EntityExtractTask.py
instruction_ner/formatters/instances/EntityTypeTask.py
instruction_ner/formatters/instances/NERTask.py
instruction_ner/formatters/instances/__init__.py
instruction_ner/readers/__init__.py
instruction_ner/readers/conll.py
instruction_ner/readers/mit.py
instruction_ner/readers/spacy.py
instruction_ner/utils/__init__.py
instruction_ner/utils/evaluate_utils.py
instruction_ner/utils/train_utils.py
instruction_ner/utils/utils.py
instruction_ner-0.1.6.dist-info/LICENSE
instruction_ner-0.1.6.dist-info/METADATA
instruction_ner-0.1.6.dist-info/WHEEL
instruction_ner-0.1.6.dist-info/entry_points.txt
instruction_ner-0.1.6.dist-info/top_level.txt
instruction_ner-0.1.6.dist-info/RECORD
