Metadata-Version: 2.1
Name: instruction-ner
Version: 0.1.6
Summary: Unofficial implementation of InstructionNER
Home-page: https://github.com/ovbystrova/InstructionNER
Author: Olga Bystrova
Author-email: bystrovaolgavl@gmail.com
Keywords: python,nlp,deep learning,ner,t5
Classifier: Programming Language :: Python :: 3.8
Classifier: Programming Language :: Python :: 3.9
Classifier: License :: OSI Approved :: MIT License
Classifier: Intended Audience :: Developers
License-File: LICENSE
Requires-Dist: dataclasses (==0.6)
Requires-Dist: openpyxl (==3.0.10)
Requires-Dist: pandas (==1.4.3)
Requires-Dist: pyyaml (==6.0)
Requires-Dist: SentencePiece (==0.1.96)
Requires-Dist: scikit-learn (==1.1.2)
Requires-Dist: torch (==1.13.1)
Requires-Dist: tensorboard (==2.9.1)
Requires-Dist: tokenizers (==0.13.2)
Requires-Dist: transformers (==4.27.1)
